{
  "Somtum Thai": "/dishes/somtum-thai.jpg",
  "Larb Moo Tod": "/dishes/larb-moo-tod.jpg",
  "Pad Thai Goong": "/dishes/pad-thai-goong.jpg",
  "Gaeng Keow Wan Gai": "/dishes/gaeng-keow-wan-gai.jpg",
  "Nam Tok Moo": "/dishes/nam-tok-moo.jpg",
  "Sukhothai Noodle": "/dishes/sukhothai-noodle.jpg",
  "Khao Soi Gai": "/dishes/khao-soi-gai.jpg",
  "Ba Mii Pu": "/dishes/ba-mii-pu.jpg",
  "Tom Yum Noodle Soup": "/dishes/tom-yum-noodle-soup.jpg",
  "Moo Ping": "/dishes/moo-ping.jpg",
  "Kanom Jeen Nam Ya": "/dishes/kanom-jeen-nam-ya.jpg",
  "Coconut Crab Curry": "/dishes/coconut-crab-curry.jpg",
  "Crab Fried Rice": "/dishes/crab-fried-rice.jpg",
  "Zabb Wings": "/dishes/zabb-wings.jpg",
  "Whole Branzino": "/dishes/whole-branzino.jpg",
  "Pork Cheek Chili Garlic": "/dishes/pork-cheek-chili-garlic.jpg",
  "Shrimp Paste Rice": "/dishes/shrimp-paste-rice.jpg",
  "Thai Disco Fries": "/dishes/thai-disco-fries.jpg",
  "Coconut Pancakes": "/dishes/coconut-pancakes.jpg",
  "Drunken Dumplings": "/dishes/drunken-dumplings.jpg",
  "Roti Kabocha": "/dishes/roti-kabocha.jpg",
  "Khao Soi": "/dishes/khao-soi.jpg",
  "Omakase": "/dishes/omakase.jpg",
  "Toro Nigiri": "/dishes/toro-nigiri.jpg",
  "Uni Nigiri": "/dishes/uni-nigiri.jpg",
  "Salmon Sashimi": "/dishes/salmon-sashimi.jpg",
  "Yellowtail Hand Roll": "/dishes/yellowtail-hand-roll.jpg",
  "Chirashi Bowl": "/dishes/chirashi-bowl.jpg",
  "21-Course Omakase": "/dishes/21-course-omakase.jpg",
  "Kohada Nigiri": "/dishes/kohada-nigiri.jpg",
  "Anago Nigiri": "/dishes/anago-nigiri.jpg",
  "Tamago": "/dishes/tamago.jpg",
  "Seasonal Sashimi Plate": "/dishes/seasonal-sashimi-plate.jpg",
  "Kitsune Udon": "/dishes/kitsune-udon.jpg",
  "Nabeyaki Udon": "/dishes/nabeyaki-udon.jpg",
  "Curry Udon": "/dishes/curry-udon.jpg",
  "Cold Zaru Udon": "/dishes/cold-zaru-udon.jpg",
  "Agedashi Tofu": "/dishes/agedashi-tofu.jpg",
  "Karaage": "/dishes/karaage.jpg",
  "Hire Katsu Set": "/dishes/hire-katsu-set.jpg",
  "Rosu Katsu Set": "/dishes/rosu-katsu-set.jpg",
  "Chicken Katsu Set": "/dishes/chicken-katsu-set.jpg",
  "Katsu Curry": "/dishes/katsu-curry.jpg",
  "Katsu Don": "/dishes/katsu-don.jpg",
  "Spaghetti Cacio e Pepe": "/dishes/spaghetti-cacio-e-pepe.jpg",
  "Beef Carpaccio": "/dishes/beef-carpaccio.jpg",
  "Ricotta Gnudi": "/dishes/ricotta-gnudi.jpg",
  "Grilled Branzino": "/dishes/grilled-branzino.jpg",
  "Burrata": "/dishes/burrata.jpg",
  "Olive Oil Cake": "/dishes/olive-oil-cake.jpg",
  "Carciofi Fritti": "/dishes/carciofi-fritti.jpg",
  "Tonnarelli Cacio e Pepe": "/dishes/tonnarelli-cacio-e-pepe.jpg",
  "Pappardelle al Ragu": "/dishes/pappardelle-al-ragu.jpg",
  "Insalata Verde": "/dishes/insalata-verde.jpg",
  "Pollo Arrosto": "/dishes/pollo-arrosto.jpg",
  "Panna Cotta": "/dishes/panna-cotta.jpg",
  "Pinwheel Lasagna": "/dishes/pinwheel-lasagna.jpg",
  "Chrysanthemum Salad": "/dishes/chrysanthemum-salad.jpg",
  "Fuzi Bolognese": "/dishes/fuzi-bolognese.jpg",
  "Meatballs al Forno": "/dishes/meatballs-al-forno.jpg",
  "Pork Chop Milanese": "/dishes/pork-chop-milanese.jpg",
  "Black Cocoa Tiramisu": "/dishes/black-cocoa-tiramisu.jpg",
  "Taco de Adobada": "/dishes/taco-de-adobada.jpg",
  "Taco de Asada": "/dishes/taco-de-asada.jpg",
  "Taco de Pollo": "/dishes/taco-de-pollo.jpg",
  "Quesadilla de Asada": "/dishes/quesadilla-de-asada.jpg",
  "Taco de Nopal": "/dishes/taco-de-nopal.jpg",
  "Horchata": "/dishes/horchata.jpg",
  "Mulita de Adobada": "/dishes/mulita-de-adobada.jpg",
  "Guacamole Clasico": "/dishes/guacamole-clasico.jpg",
  "Fish Tacos": "/dishes/fish-tacos.jpg",
  "Pork Belly Tostada": "/dishes/pork-belly-tostada.jpg",
  "Enchiladas de Mole": "/dishes/enchiladas-de-mole.jpg",
  "Tacos de Carnitas": "/dishes/tacos-de-carnitas.jpg",
  "Churros con Chocolate": "/dishes/churros-con-chocolate.jpg",
  "Al Pastor Tacos": "/dishes/al-pastor-tacos.jpg",
  "Birria Tacos": "/dishes/birria-tacos.jpg",
  "Elote": "/dishes/elote.jpg",
  "Burrito de Pollo": "/dishes/burrito-de-pollo.jpg",
  "Nachos Supremos": "/dishes/nachos-supremos.jpg",
  "Tres Leches Cake": "/dishes/tres-leches-cake.jpg",
  "Butter Chicken": "/dishes/butter-chicken.jpg",
  "Lamb Seekh Kebab": "/dishes/lamb-seekh-kebab.jpg",
  "Chicken Biryani": "/dishes/chicken-biryani.jpg",
  "Fish Curry": "/dishes/fish-curry.jpg",
  "Garlic Naan": "/dishes/garlic-naan.jpg",
  "Gulab Jamun": "/dishes/gulab-jamun.jpg",
  "Chicken Tikka Masala": "/dishes/chicken-tikka-masala.jpg",
  "Saag Paneer": "/dishes/saag-paneer.jpg",
  "Lamb Rogan Josh": "/dishes/lamb-rogan-josh.jpg",
  "Samosa Chaat": "/dishes/samosa-chaat.jpg",
  "Dal Makhani": "/dishes/dal-makhani.jpg",
  "Tandoori Mixed Grill": "/dishes/tandoori-mixed-grill.jpg",
  "Chicken Vindaloo": "/dishes/chicken-vindaloo.jpg",
  "Malai Kofta": "/dishes/malai-kofta.jpg",
  "Tandoori Chicken": "/dishes/tandoori-chicken.jpg",
  "Aloo Gobi": "/dishes/aloo-gobi.jpg",
  "Mango Lassi": "/dishes/mango-lassi.jpg",
  "Original Egg Roll": "/dishes/original-egg-roll.jpg",
  "Shrimp Ha Gow": "/dishes/shrimp-ha-gow.jpg",
  "Siu Mai": "/dishes/siu-mai.jpg",
  "Turnip Cake": "/dishes/turnip-cake.jpg",
  "Roast Pork Bun": "/dishes/roast-pork-bun.jpg",
  "Pan Fried Noodles": "/dishes/pan-fried-noodles.jpg",
  "Salt and Pepper Squid": "/dishes/salt-and-pepper-squid.jpg",
  "Har Gow": "/dishes/har-gow.jpg",
  "Char Siu Bao": "/dishes/char-siu-bao.jpg",
  "Spare Ribs with Black Bean": "/dishes/spare-ribs-with-black-bean.jpg",
  "Cheung Fun": "/dishes/cheung-fun.jpg",
  "Peking Duck": "/dishes/peking-duck.jpg",
  "Lo Mein": "/dishes/lo-mein.jpg",
  "Dan Tat": "/dishes/dan-tat.jpg",
  "Liang Pi Cold Skin Noodles": "/dishes/liang-pi-cold-skin-noodles.jpg",
  "Lamb Burger": "/dishes/lamb-burger.jpg",
  "Stewed Pork Burger": "/dishes/stewed-pork-burger.jpg",
  "Spicy and Tingly Beef Hand-Ripped Noodles": "/dishes/spicy-and-tingly-beef-hand-ripped-noodles.jpg",
  "N1 Spicy Cumin Lamb Noodle Soup": "/dishes/n1-spicy-cumin-lamb-noodle-soup.jpg",
  "Premium Beef Combo": "/dishes/premium-beef-combo.jpg",
  "Pork Belly": "/dishes/pork-belly.jpg",
  "Cheese Corn": "/dishes/cheese-corn.jpg",
  "Steamed Egg": "/dishes/steamed-egg.jpg",
  "Bulgogi": "/dishes/bulgogi.jpg",
  "Japchae": "/dishes/japchae.jpg",
  "Kimchi Jjigae": "/dishes/kimchi-jjigae.jpg",
  "Bossam": "/dishes/bossam.jpg",
  "Seafood Pancake": "/dishes/seafood-pancake.jpg",
  "Spicy Seafood Tofu Stew": "/dishes/spicy-seafood-tofu-stew.jpg",
  "Grilled Mackerel": "/dishes/grilled-mackerel.jpg",
  "Bibimbap": "/dishes/bibimbap.jpg",
  "Tteokbokki": "/dishes/tteokbokki.jpg",
  "Uni Bibimbap": "/dishes/uni-bibimbap.jpg",
  "Kimchi Pancake": "/dishes/kimchi-pancake.jpg",
  "Gochujang Glazed Squid": "/dishes/gochujang-glazed-squid.jpg",
  "Kimchi Fried Rice": "/dishes/kimchi-fried-rice.jpg",
  "Korean Fried Chicken": "/dishes/korean-fried-chicken.jpg",
  "Soondubu Jjigae": "/dishes/soondubu-jjigae.jpg",
  "Grilled Octopus": "/dishes/grilled-octopus.jpg",
  "Lamb Chops": "/dishes/lamb-chops.jpg",
  "Branzino": "/dishes/branzino.jpg",
  "Hummus": "/dishes/hummus.jpg",
  "Shakshuka": "/dishes/shakshuka.jpg",
  "Mediterranean Salad": "/dishes/mediterranean-salad.jpg",
  "Falafel": "/dishes/falafel.jpg",
  "Braised Lamb Shank": "/dishes/braised-lamb-shank.jpg",
  "Flaming Saganaki": "/dishes/flaming-saganaki.jpg",
  "Taramasalata": "/dishes/taramasalata.jpg",
  "Duck Borek": "/dishes/duck-borek.jpg",
  "Moroccan Fried Chicken": "/dishes/moroccan-fried-chicken.jpg",
  "Baklava": "/dishes/baklava.jpg",
  "Buttermilk Biscuit Sandwich": "/dishes/buttermilk-biscuit-sandwich.jpg",
  "Low Country Meatloaf": "/dishes/low-country-meatloaf.jpg",
  "Shrimp and Grits": "/dishes/shrimp-and-grits.jpg",
  "Catfish Tacos": "/dishes/catfish-tacos.jpg",
  "Mac and Cheese": "/dishes/mac-and-cheese.jpg",
  "Sausage Gravy Biscuit": "/dishes/sausage-gravy-biscuit.jpg",
  "Pickle Plate": "/dishes/pickle-plate.jpg",
  "The Smith Burger": "/dishes/the-smith-burger.jpg",
  "Kale and Quinoa Salad": "/dishes/kale-and-quinoa-salad.jpg",
  "Pan-Roasted Branzino": "/dishes/pan-roasted-branzino.jpg",
  "Pot of Mussels": "/dishes/pot-of-mussels.jpg",
  "Truffle Fries": "/dishes/truffle-fries.jpg",
  "Pan-Roasted Chicken": "/dishes/pan-roasted-chicken.jpg",
  "Market Plate": "/dishes/market-plate.jpg",
  "Westville Burger": "/dishes/westville-burger.jpg",
  "Grilled Salmon": "/dishes/grilled-salmon.jpg",
  "Kale Caesar Salad": "/dishes/kale-caesar-salad.jpg",
  "Sweet Potato Fries": "/dishes/sweet-potato-fries.jpg",
  "Roasted Cauliflower Steak": "/dishes/roasted-cauliflower-steak.jpg",
  "Special Pho": "/dishes/special-pho.jpg",
  "Summer Rolls": "/dishes/summer-rolls.jpg",
  "Braised Beef Banh Mi": "/dishes/braised-beef-banh-mi.jpg",
  "Bun Cha": "/dishes/bun-cha.jpg",
  "Turmeric Fish": "/dishes/turmeric-fish.jpg",
  "Coconut Coffee Panna Cotta": "/dishes/coconut-coffee-panna-cotta.jpg",
  "Saigon Pho": "/dishes/saigon-pho.jpg",
  "Banh Mi Dac Biet": "/dishes/banh-mi-dac-biet.jpg",
  "Bun Bo Hue": "/dishes/bun-bo-hue.jpg",
  "Lemongrass Chicken": "/dishes/lemongrass-chicken.jpg",
  "Vietnamese Iced Coffee": "/dishes/vietnamese-iced-coffee.jpg"
}